controller.v
// controller code
module controller(ld_item,ld_price,ld_bal,ld_coin,reset,bal_sel,done,clk,lt,gt,eq,start);
input lt,gt,eq,start,clk,reset;
output reg ld_item,ld_price,ld_bal,ld_coin,done;
output reg [1:0] bal_sel;
reg [2:0] state;
parameter IDLE=3'b000, ITEM_SELECT=3'b001, COIN_ACCEPT=3'b010, BAL_UPD=3'b011, DISPENSE=3'b100;

always @(posedge clk)
begin
if(reset)
state<=IDLE;
else 
begin
case(state)
IDLE: if(start)
state<=ITEM_SELECT;
ITEM_SELECT: state<=COIN_ACCEPT;
COIN_ACCEPT: state<=BAL_UPD;
BAL_UPD: if(lt)
state<=COIN_ACCEPT;
else
state<=DISPENSE;
DISPENSE: state<=IDLE;
default: state<=IDLE;
endcase
end
end

always @(*)
begin
ld_item=0;ld_price=0;ld_bal=0;ld_coin=0;done=0;bal_sel=0;
case(state)
IDLE:begin
ld_item=0;ld_price=0;ld_bal=1;ld_coin=0;done=0;bal_sel=0;
end
ITEM_SELECT:begin
ld_item=1;
end
COIN_ACCEPT:begin
ld_coin=1;ld_price=1;
end
BAL_UPD:begin
bal_sel=1;ld_bal=1;
end
DISPENSE:begin
bal_sel=2;ld_bal=1;done=1;
end
default: ;
endcase
end

endmodule

datapath.v
// datapath code for vending machine

// top level module
module datapath(lt,gt,eq,ld_item,ld_price,ld_bal,ld_coin,coin_sel,bal_sel,item_sel,clk,reset);
parameter ITEM0_PRICE=8'd10,ITEM1_PRICE=8'd20,ITEM2_PRICE=8'd50,ITEM3_PRICE=8'd100;
parameter COIN0_PRICE=8'd0,COIN1_PRICE=8'd5,COIN2_PRICE=8'd10,COIN3_PRICE=8'd20;
output lt,gt,eq;
input [1:0] bal_sel,coin_sel,item_sel;
input ld_item,ld_price,ld_bal,ld_coin,clk,reset;
wire [7:0] item_out,price_out,bal_out,coin_mux_out,coin_out,sub_out,add_out,bal_mux_out;
wire [1:0] item_reg_out;
mux4to1 ITEM(.out(item_out),.in({ITEM3_PRICE, ITEM2_PRICE, ITEM1_PRICE, ITEM0_PRICE}),.sel(item_reg_out));
reg2 ITEM_REG(item_reg_out,item_sel,ld_item,clk,reset);
reg8 PRICE(price_out,item_out,ld_price,clk,reset);
comp COMP(lt,gt,eq,bal_out,price_out);
reg8 BAL_REG(bal_out,bal_mux_out,ld_bal,clk,reset);
adder ADDER(add_out,coin_out,bal_out);
sub SUB(sub_out,bal_out,price_out);
reg8 COIN_REG(coin_out,coin_mux_out,ld_coin,clk,reset);
mux4to1 COIN(.out(coin_mux_out),.in({COIN3_PRICE,COIN2_PRICE,COIN1_PRICE,COIN0_PRICE}),.sel(coin_sel));
mux4to1 MUX(.out(bal_mux_out),.in({bal_out,sub_out,add_out,8'd0}),.sel(bal_sel));
endmodule


// 4 to 1 mux
module mux4to1(out,in,sel);
input [31:0] in;
input [1:0] sel;
output [7:0] out;
assign out = in[sel*8 +: 8];
endmodule

// adder
module adder(sum,a,b);
input [7:0] a,b;
output [7:0] sum;
assign sum = a+b;
endmodule

// subtracter 
module sub(diff,x,y);
input [7:0] x,y;
output [7:0] diff;
assign diff = x-y;
endmodule

// comparator
module comp(lt,gt,eq,p,q);
input [7:0] p,q;
output lt,gt,eq;
assign lt = p<q;
assign gt = p>q;
assign eq = p==q;
endmodule

// 8 bit register
module reg8(out,in,ld,clk,reset);
input [7:0] in;
output reg [7:0] out;
input ld,clk,reset;
always @(posedge clk)
if(reset)
out<=8'd0;
else if(ld)
out<=in;
endmodule

// 2 bit register
module reg2(out,in,ld,clk,reset);
input [1:0] in;
output reg [1:0] out;
input ld,clk,reset;
always @(posedge clk)
if(reset)
out<=2'd0;
else if(ld)
out<=in;
endmodule

tb.v
// testbench code
module vending_test;
reg reset,start,clk;
reg [1:0] item_sel,coin_sel;
wire done;
wire lt, gt, eq;
wire ld_item, ld_price, ld_bal, ld_coin;
wire [1:0] bal_sel;
datapath d(lt,gt,eq,ld_item,ld_price,ld_bal,ld_coin,coin_sel,bal_sel,item_sel,clk,reset);
controller c(ld_item,ld_price,ld_bal,ld_coin,reset,bal_sel,done,clk,lt,gt,eq,start);

initial
begin
clk=1'b0;
reset=1'b1;
coin_sel=2'b00;
item_sel=2'b00;
#1000 $finish;
end

always 
#5 clk=~clk;

initial
begin
#10 reset=1'b0;
#10 item_sel=2'b11;
#10 start=1'b1;
#10 start=1'b0;
#20 coin_sel=2'b01;
#20 coin_sel=2'b01;
#20 coin_sel=2'b10;
#20 coin_sel=2'b10;
#20 coin_sel=2'b10;
#20 coin_sel=2'b11;
#20 coin_sel=2'b11;
#20 coin_sel=2'b10;
#20 coin_sel=2'b11;
end
initial
begin
$dumpfile("vending.vcd");
$dumpvars(0,vending_test);
$monitor("TIME:%d,PRICE:%d,COIN:%d,BALANCE:%d,DONE:%d",$time,d.price_out,d.coin_out,d.bal_out,done);
end

endmodule

vending.vcd
$date
	Tue Jan 13 22:16:05 2026
$end
$version
	Icarus Verilog
$end
$timescale
	1s
$end
$scope module vending_test $end
$var wire 1 ! lt $end
$var wire 1 " ld_price $end
$var wire 1 # ld_item $end
$var wire 1 $ ld_coin $end
$var wire 1 % ld_bal $end
$var wire 1 & gt $end
$var wire 1 ' eq $end
$var wire 1 ( done $end
$var wire 2 ) bal_sel [1:0] $end
$var reg 1 * clk $end
$var reg 2 + coin_sel [1:0] $end
$var reg 2 , item_sel [1:0] $end
$var reg 1 - reset $end
$var reg 1 . start $end
$scope module c $end
$var wire 1 * clk $end
$var wire 1 - reset $end
$var wire 1 . start $end
$var wire 1 ! lt $end
$var wire 1 & gt $end
$var wire 1 ' eq $end
$var parameter 3 / BAL_UPD $end
$var parameter 3 0 COIN_ACCEPT $end
$var parameter 3 1 DISPENSE $end
$var parameter 3 2 IDLE $end
$var parameter 3 3 ITEM_SELECT $end
$var reg 2 4 bal_sel [1:0] $end
$var reg 1 ( done $end
$var reg 1 % ld_bal $end
$var reg 1 $ ld_coin $end
$var reg 1 # ld_item $end
$var reg 1 " ld_price $end
$var reg 3 5 state [2:0] $end
$upscope $end
$scope module d $end
$var wire 2 6 bal_sel [1:0] $end
$var wire 1 * clk $end
$var wire 2 7 coin_sel [1:0] $end
$var wire 2 8 item_sel [1:0] $end
$var wire 1 % ld_bal $end
$var wire 1 $ ld_coin $end
$var wire 1 # ld_item $end
$var wire 1 " ld_price $end
$var wire 1 - reset $end
$var wire 8 9 sub_out [7:0] $end
$var wire 8 : price_out [7:0] $end
$var wire 1 ! lt $end
$var wire 2 ; item_reg_out [1:0] $end
$var wire 8 < item_out [7:0] $end
$var wire 1 & gt $end
$var wire 1 ' eq $end
$var wire 8 = coin_out [7:0] $end
$var wire 8 > coin_mux_out [7:0] $end
$var wire 8 ? bal_out [7:0] $end
$var wire 8 @ bal_mux_out [7:0] $end
$var wire 8 A add_out [7:0] $end
$var parameter 8 B COIN0_PRICE $end
$var parameter 8 C COIN1_PRICE $end
$var parameter 8 D COIN2_PRICE $end
$var parameter 8 E COIN3_PRICE $end
$var parameter 8 F ITEM0_PRICE $end
$var parameter 8 G ITEM1_PRICE $end
$var parameter 8 H ITEM2_PRICE $end
$var parameter 8 I ITEM3_PRICE $end
$scope module ADDER $end
$var wire 8 J sum [7:0] $end
$var wire 8 K b [7:0] $end
$var wire 8 L a [7:0] $end
$upscope $end
$scope module BAL_REG $end
$var wire 1 * clk $end
$var wire 1 % ld $end
$var wire 1 - reset $end
$var wire 8 M in [7:0] $end
$var reg 8 N out [7:0] $end
$upscope $end
$scope module COIN $end
$var wire 32 O in [31:0] $end
$var wire 2 P sel [1:0] $end
$var wire 8 Q out [7:0] $end
$upscope $end
$scope module COIN_REG $end
$var wire 1 * clk $end
$var wire 8 R in [7:0] $end
$var wire 1 $ ld $end
$var wire 1 - reset $end
$var reg 8 S out [7:0] $end
$upscope $end
$scope module COMP $end
$var wire 8 T p [7:0] $end
$var wire 8 U q [7:0] $end
$var wire 1 ! lt $end
$var wire 1 & gt $end
$var wire 1 ' eq $end
$upscope $end
$scope module ITEM $end
$var wire 32 V in [31:0] $end
$var wire 2 W sel [1:0] $end
$var wire 8 X out [7:0] $end
$upscope $end
$scope module ITEM_REG $end
$var wire 1 * clk $end
$var wire 2 Y in [1:0] $end
$var wire 1 # ld $end
$var wire 1 - reset $end
$var reg 2 Z out [1:0] $end
$upscope $end
$scope module MUX $end
$var wire 32 [ in [31:0] $end
$var wire 2 \ sel [1:0] $end
$var wire 8 ] out [7:0] $end
$upscope $end
$scope module PRICE $end
$var wire 1 * clk $end
$var wire 8 ^ in [7:0] $end
$var wire 1 " ld $end
$var wire 1 - reset $end
$var reg 8 _ out [7:0] $end
$upscope $end
$scope module SUB $end
$var wire 8 ` x [7:0] $end
$var wire 8 a y [7:0] $end
$var wire 8 b diff [7:0] $end
$upscope $end
$upscope $end
$upscope $end
$enddefinitions $end
$comment Show the parameter values. $end
$dumpall
b1100100 I
b110010 H
b10100 G
b1010 F
b10100 E
b1010 D
b101 C
b0 B
b1 3
b0 2
b100 1
b10 0
b11 /
$end
#0
$dumpvars
bx b
bx a
bx `
bx _
bx ^
bx ]
bx \
bx00000000 [
bx Z
b0 Y
bx X
bx W
b1100100001100100001010000001010 V
bx U
bx T
bx S
b0 R
b0 Q
b0 P
b10100000010100000010100000000 O
bx N
bx M
bx L
bx K
bx J
bx A
bx @
bx ?
b0 >
bx =
bx <
bx ;
bx :
bx 9
b0 8
b0 7
bx 6
bx 5
bx 4
x.
1-
b0 ,
b0 +
0*
bx )
x(
x'
x&
x%
x$
x#
x"
x!
$end
#5
b0 @
b0 M
b0 ]
b0 )
b0 4
b0 6
b0 \
0(
0$
1%
0"
0#
b1010 <
b1010 X
b1010 ^
b0 ;
b0 W
b0 Z
b0 9
b0 b
1'
0&
0!
b0 :
b0 U
b0 _
b0 a
b0 A
b0 J
b0 [
b0 ?
b0 K
b0 N
b0 T
b0 `
b0 =
b0 L
b0 S
b0 5
1*
#10
0*
0-
#15
1*
#20
0*
b11 ,
b11 8
b11 Y
#25
1*
#30
0*
1.
#35
1#
0%
b1 5
1*
#40
0*
0.
#45
1"
1$
0#
b1100100 <
b1100100 X
b1100100 ^
b11 ;
b11 W
b11 Z
b10 5
1*
#50
0*
#55
1%
b1 )
b1 4
b1 6
b1 \
0$
0"
b11 5
b100111000000000000000000 [
b10011100 9
b10011100 b
0'
1!
b1100100 :
b1100100 U
b1100100 _
b1100100 a
1*
#60
0*
b101 >
b101 Q
b101 R
b1 +
b1 7
b1 P
#65
1"
1$
b0 )
b0 4
b0 6
b0 \
0%
b10 5
1*
#70
0*
#75
1%
b101 @
b101 M
b101 ]
b1 )
b1 4
b1 6
b1 \
0$
0"
b11 5
b100111000000010100000000 [
b101 A
b101 J
b101 =
b101 L
b101 S
1*
#80
0*
#85
1"
1$
b0 )
b0 4
b0 6
b0 \
0%
b10100001 9
b10100001 b
b0 @
b0 M
b0 ]
b1010 A
b1010 J
b101101000010000101000000000 [
b101 ?
b101 K
b101 N
b101 T
b101 `
b10 5
1*
#90
0*
#95
1%
b1010 @
b1010 M
b1010 ]
b1 )
b1 4
b1 6
b1 \
0$
0"
b11 5
1*
#100
0*
b1010 >
b1010 Q
b1010 R
b10 +
b10 7
b10 P
#105
1"
1$
b0 )
b0 4
b0 6
b0 \
0%
b10100110 9
b10100110 b
b0 @
b0 M
b0 ]
b1111 A
b1111 J
b1010101001100000111100000000 [
b1010 ?
b1010 K
b1010 N
b1010 T
b1010 `
b10 5
1*
#110
0*
#115
1%
b10100 @
b10100 M
b10100 ]
b1 )
b1 4
b1 6
b1 \
0$
0"
b11 5
b1010101001100001010000000000 [
b10100 A
b10100 J
b1010 =
b1010 L
b1010 S
1*
#120
0*
#125
1"
1$
b0 )
b0 4
b0 6
b0 \
0%
b10110000 9
b10110000 b
b0 @
b0 M
b0 ]
b11110 A
b11110 J
b10100101100000001111000000000 [
b10100 ?
b10100 K
b10100 N
b10100 T
b10100 `
b10 5
1*
#130
0*
#135
1%
b11110 @
b11110 M
b11110 ]
b1 )
b1 4
b1 6
b1 \
0$
0"
b11 5
1*
#140
0*
#145
1"
1$
b0 )
b0 4
b0 6
b0 \
0%
b10111010 9
b10111010 b
b0 @
b0 M
b0 ]
b101000 A
b101000 J
b11110101110100010100000000000 [
b11110 ?
b11110 K
b11110 N
b11110 T
b11110 `
b10 5
1*
#150
0*
#155
1%
b101000 @
b101000 M
b101000 ]
b1 )
b1 4
b1 6
b1 \
0$
0"
b11 5
1*
#160
0*
b10100 >
b10100 Q
b10100 R
b11 +
b11 7
b11 P
#165
1"
1$
b0 )
b0 4
b0 6
b0 \
0%
b11000100 9
b11000100 b
b0 @
b0 M
b0 ]
b110010 A
b110010 J
b101000110001000011001000000000 [
b101000 ?
b101000 K
b101000 N
b101000 T
b101000 `
b10 5
1*
#170
0*
#175
1%
b111100 @
b111100 M
b111100 ]
b1 )
b1 4
b1 6
b1 \
0$
0"
b11 5
b101000110001000011110000000000 [
b111100 A
b111100 J
b10100 =
b10100 L
b10100 S
1*
#180
0*
#185
1"
1$
b0 )
b0 4
b0 6
b0 \
0%
b11011000 9
b11011000 b
b0 @
b0 M
b0 ]
b1010000 A
b1010000 J
b111100110110000101000000000000 [
b111100 ?
b111100 K
b111100 N
b111100 T
b111100 `
b10 5
1*
#190
0*
#195
1%
b1010000 @
b1010000 M
b1010000 ]
b1 )
b1 4
b1 6
b1 \
0$
0"
b11 5
1*
#200
0*
b1010 >
b1010 Q
b1010 R
b10 +
b10 7
b10 P
#205
1"
1$
b0 )
b0 4
b0 6
b0 \
0%
b11101100 9
b11101100 b
b0 @
b0 M
b0 ]
b1100100 A
b1100100 J
b1010000111011000110010000000000 [
b1010000 ?
b1010000 K
b1010000 N
b1010000 T
b1010000 `
b10 5
1*
#210
0*
#215
1%
b1011010 @
b1011010 M
b1011010 ]
b1 )
b1 4
b1 6
b1 \
0$
0"
b11 5
b1010000111011000101101000000000 [
b1011010 A
b1011010 J
b1010 =
b1010 L
b1010 S
1*
#220
0*
b10100 >
b10100 Q
b10100 R
b11 +
b11 7
b11 P
#225
1"
1$
b0 )
b0 4
b0 6
b0 \
0%
b11110110 9
b11110110 b
b0 @
b0 M
b0 ]
b1100100 A
b1100100 J
b1011010111101100110010000000000 [
b1011010 ?
b1011010 K
b1011010 N
b1011010 T
b1011010 `
b10 5
1*
#230
0*
#235
1%
b1101110 @
b1101110 M
b1101110 ]
b1 )
b1 4
b1 6
b1 \
0$
0"
b11 5
b1011010111101100110111000000000 [
b1101110 A
b1101110 J
b10100 =
b10100 L
b10100 S
1*
#240
0*
#245
1"
1$
b0 )
b0 4
b0 6
b0 \
0%
0!
1&
b1010 9
b1010 b
b0 @
b0 M
b0 ]
b10000010 A
b10000010 J
b1101110000010101000001000000000 [
b1101110 ?
b1101110 K
b1101110 N
b1101110 T
b1101110 `
b10 5
1*
#250
0*
#255
1%
b10000010 @
b10000010 M
b10000010 ]
b1 )
b1 4
b1 6
b1 \
0$
0"
b11 5
1*
#260
0*
#265
1(
b10 )
b10 4
b10 6
b10 \
1%
b11110 9
b11110 b
b11110 @
b11110 M
b11110 ]
b10010110 A
b10010110 J
b10000010000111101001011000000000 [
b10000010 ?
b10000010 K
b10000010 N
b10000010 T
b10000010 `
b100 5
1*
#270
0*
#275
b0 )
b0 4
b0 6
b0 \
0(
1%
b0 5
1!
0&
b0 @
b0 M
b0 ]
b10111010 9
b10111010 b
b110010 A
b110010 J
b11110101110100011001000000000 [
b11110 ?
b11110 K
b11110 N
b11110 T
b11110 `
1*
#280
0*
#285
b10011100 9
b10011100 b
b10100 A
b10100 J
b100111000001010000000000 [
b0 ?
b0 K
b0 N
b0 T
b0 `
1*
